rddensity/__init__.py
rddensity/funs.py
rddensity/rdbwdensity.py
rddensity/rddensity.py
rddensity/rdplotdensity.py
rddensity-2.4.6.dist-info/METADATA
rddensity-2.4.6.dist-info/WHEEL
rddensity-2.4.6.dist-info/top_level.txt
rddensity-2.4.6.dist-info/RECORD
