Metadata-Version: 2.2
Name: rddensity
Version: 2.4.6
Summary: Mainpulation testing based on Density Discontinuity
Home-page: https://github.com/rdpackages/rddensity
Author: Rajita Chandak
Author-email: rchandak@princeton.edu
Project-URL: Bug Tracker, https://github.com/rdpackages/rddensity/issues
Classifier: Programming Language :: Python :: 3
Classifier: License :: OSI Approved :: MIT License
Classifier: Operating System :: OS Independent
Requires-Python: >=3.7
Requires-Dist: numpy
Requires-Dist: pandas
Requires-Dist: scipy
Requires-Dist: sympy
Requires-Dist: plotnine
Requires-Dist: lpdensity
